{"_type":"export","__export_format":4,"__export_date":"2024-03-11T17:02:03.501Z","__export_source":"insomnia.desktop.app:v8.6.1","resources":[{"_id":"req_0c5f1d3dcb024e4bbb8ba42418024d70","parentId":"fld_163c74e5798b466fb126b2bfbaf12ba9","modified":1710046979954,"created":1710045875438,"url":"{{ _.BASE_URL }}/cars/00df1bee-1539-4b82-9277-777ecd553322","name":"Update","description":"","method":"PUT","body":{"mimeType":"application/json","text":"{\n\t\"name\": \"HB20\",\n\t\"brand\": \"Hyundai\",\n\t\"year\": \"2016\",\n\t\"color\": \"Prata\"\n}"},"parameters":[],"headers":[{"name":"Content-Type","value":"application/json"},{"name":"User-Agent","value":"insomnia/8.6.1"}],"authentication":{},"metaSortKey":-1710045875438,"isPrivate":false,"pathParameters":[],"settingStoreCookies":true,"settingSendCookies":true,"settingDisableRenderRequestBody":false,"settingEncodeUrl":true,"settingRebuildPath":true,"settingFollowRedirects":"global","_type":"request"},{"_id":"fld_163c74e5798b466fb126b2bfbaf12ba9","parentId":"wrk_5dba9cbd3ea54f38af8f4a1d419c6812","modified":1710041217194,"created":1710041217194,"name":"Car","description":"","environment":{},"environmentPropertyOrder":null,"metaSortKey":-1710041217194,"_type":"request_group"},{"_id":"wrk_5dba9cbd3ea54f38af8f4a1d419c6812","parentId":null,"modified":1709587826080,"created":1709587826080,"name":"API","description":"","scope":"collection","_type":"workspace"},{"_id":"req_39f35e9877554305843adb45a60a8d3f","parentId":"fld_163c74e5798b466fb126b2bfbaf12ba9","modified":1710103639497,"created":1710103575769,"url":"{{ _.BASE_URL }}/cars/93891124-0af1-4aec-9f0a-418700597e14","name":"Delete","description":"","method":"DELETE","body":{},"parameters":[],"headers":[{"name":"User-Agent","value":"insomnia/8.6.1"}],"authentication":{},"metaSortKey":-1710044349829,"isPrivate":false,"pathParameters":[],"settingStoreCookies":true,"settingSendCookies":true,"settingDisableRenderRequestBody":false,"settingEncodeUrl":true,"settingRebuildPath":true,"settingFollowRedirects":"global","_type":"request"},{"_id":"req_4702b0f4e3ee47a6aa84cdfef418b212","parentId":"fld_163c74e5798b466fb126b2bfbaf12ba9","modified":1710104785408,"created":1710042824220,"url":"{{ _.BASE_URL }}/cars/00df1bee-1539-4b82-9277-777ecd553322","name":"Get Detail","description":"","method":"GET","body":{},"parameters":[],"headers":[{"name":"User-Agent","value":"insomnia/8.6.1"}],"authentication":{},"metaSortKey":-1710042824220,"isPrivate":false,"pathParameters":[],"settingStoreCookies":true,"settingSendCookies":true,"settingDisableRenderRequestBody":false,"settingEncodeUrl":true,"settingRebuildPath":true,"settingFollowRedirects":"global","_type":"request"},{"_id":"req_e8f06a3776774291871eab64bfa52b63","parentId":"fld_163c74e5798b466fb126b2bfbaf12ba9","modified":1710107001321,"created":1710105667122,"url":"{{ _.BASE_URL }}/list-car/cltkv0l610000xgo17h8q1bf0","name":"List all","description":"","method":"GET","body":{},"parameters":[],"headers":[{"name":"User-Agent","value":"insomnia/8.6.1"}],"authentication":{},"metaSortKey":-1710042021556.5,"isPrivate":false,"pathParameters":[],"settingStoreCookies":true,"settingSendCookies":true,"settingDisableRenderRequestBody":false,"settingEncodeUrl":true,"settingRebuildPath":true,"settingFollowRedirects":"global","_type":"request"},{"_id":"req_4ffeb84430654dbe839e488f331cbc52","parentId":"fld_163c74e5798b466fb126b2bfbaf12ba9","modified":1710042865438,"created":1710041218893,"url":"{{ _.BASE_URL }}/cars","name":"Create","description":"","method":"POST","body":{"mimeType":"application/json","text":"{\n\t\"userId\": \"cltkv0l610000xgo17h8q1bf0\",\n\t\"name\": \"Uno\",\n\t\"brand\": \"Fiat\",\n\t\"year\": \"1999\",\n\t\"color\": \"Vermelho\"\n}"},"parameters":[],"headers":[{"name":"Content-Type","value":"application/json"},{"name":"User-Agent","value":"insomnia/8.6.1"}],"authentication":{},"metaSortKey":-1710041218893,"isPrivate":false,"pathParameters":[],"settingStoreCookies":true,"settingSendCookies":true,"settingDisableRenderRequestBody":false,"settingEncodeUrl":true,"settingRebuildPath":true,"settingFollowRedirects":"global","_type":"request"},{"_id":"req_cb11e9f953774f239ffd961efd015c39","parentId":"fld_6e062cefe0ee4235871c50e6b6cc8d0c","modified":1710035660019,"created":1710035564003,"url":"{{ _.BASE_URL }}/sessions","name":"Auth","description":"","method":"POST","body":{"mimeType":"application/json","text":"{\n\t\"email\": \"apolo@email.com\",\n\t\"password\": \"senha123\"\n}"},"parameters":[],"headers":[{"name":"Content-Type","value":"application/json"},{"name":"User-Agent","value":"insomnia/8.6.1"}],"authentication":{},"metaSortKey":-1710035564003,"isPrivate":false,"pathParameters":[],"settingStoreCookies":true,"settingSendCookies":true,"settingDisableRenderRequestBody":false,"settingEncodeUrl":true,"settingRebuildPath":true,"settingFollowRedirects":"global","_type":"request"},{"_id":"fld_6e062cefe0ee4235871c50e6b6cc8d0c","parentId":"wrk_5dba9cbd3ea54f38af8f4a1d419c6812","modified":1710035561804,"created":1710035561804,"name":"Session","description":"","environment":{},"environmentPropertyOrder":null,"metaSortKey":-1710035561804,"_type":"request_group"},{"_id":"req_e862897a06cf4dc0ac9698a5798eb83e","parentId":"fld_c3bbfb6ca29e4c94939a015c8fdd31bf","modified":1710106130153,"created":1709587840582,"url":"{{ _.BASE_URL }}/users","name":"Create user","description":"","method":"POST","body":{"mimeType":"application/json","text":"{\n\t\"name\": \"Apolof\",\n\t\"email\": \"apolof@email.com\",\n\t\"password\": \"senha123\"\n}"},"parameters":[],"headers":[{"name":"Content-Type","value":"application/json"},{"name":"User-Agent","value":"insomnia/8.6.1"}],"authentication":{},"metaSortKey":-1709587840582,"isPrivate":false,"pathParameters":[],"settingStoreCookies":true,"settingSendCookies":true,"settingDisableRenderRequestBody":false,"settingEncodeUrl":true,"settingRebuildPath":true,"settingFollowRedirects":"global","_type":"request"},{"_id":"fld_c3bbfb6ca29e4c94939a015c8fdd31bf","parentId":"wrk_5dba9cbd3ea54f38af8f4a1d419c6812","modified":1709587838253,"created":1709587834072,"name":"User","description":"","environment":{},"environmentPropertyOrder":null,"metaSortKey":-1709587834072,"_type":"request_group"},{"_id":"env_c79d2378404ffc06fe518b4262ba31e8acf5fbae","parentId":"wrk_5dba9cbd3ea54f38af8f4a1d419c6812","modified":1710035620167,"created":1709587826082,"name":"Base Environment","data":{"BASE_URL":"http://localhost:3333/"},"dataPropertyOrder":{"&":["BASE_URL"]},"color":null,"isPrivate":false,"metaSortKey":1709587826082,"_type":"environment"},{"_id":"jar_c79d2378404ffc06fe518b4262ba31e8acf5fbae","parentId":"wrk_5dba9cbd3ea54f38af8f4a1d419c6812","modified":1709587826083,"created":1709587826083,"name":"Default Jar","cookies":[],"_type":"cookie_jar"},{"_id":"env_e097c7ea5575484aa38b2f379dd46ddd","parentId":"env_c79d2378404ffc06fe518b4262ba31e8acf5fbae","modified":1710035665677,"created":1710035634556,"name":"Dev","data":{"BASE_URL":"http://localhost:3333"},"dataPropertyOrder":{"&":["BASE_URL"]},"color":"#10a228","isPrivate":false,"metaSortKey":1710035634555,"_type":"environment"}]}